hiedwinlan/__init__.py
hiedwinlan/__main__.py
hiedwinlan-0.1.0.dist-info/METADATA
hiedwinlan-0.1.0.dist-info/WHEEL
hiedwinlan-0.1.0.dist-info/top_level.txt
hiedwinlan-0.1.0.dist-info/RECORD
