Metadata-Version: 2.1
Name: hiedwinlan
Version: 0.1.0
Summary: A simple SDK that returns Hello World
Home-page: https://github.com/yourusername/hiedwinlan
Author: HiedwinLan
Author-email: your.email@example.com
Classifier: Programming Language :: Python :: 3.8
Classifier: Programming Language :: Python :: 3.9
Classifier: Programming Language :: Python :: 3.10
Classifier: Programming Language :: Python :: 3.11
Classifier: License :: OSI Approved :: MIT License
Classifier: Operating System :: OS Independent
Requires-Python: >=3.8
